Metadata-Version: 2.1
Name: coll-filter
Version: 1.3.2
Summary: Collaborative Filtering with multi-process parallelism.
Home-page: https://gitee.com/summry/myai
Author: summy
Author-email: xiazhongbiao@126.com
License: UNKNOWN
Keywords: Collaborative Filtering,recommend
Platform: UNKNOWN
Requires-Python: >=3.6
